CHANGES.rst
LICENSE
MANIFEST.in
README.rst
setup.cfg
setup.py
myasuda/sphinx/__init__.py
myasuda/sphinx/erdiagram.py
sphinx_erdiagram.egg-info/PKG-INFO
sphinx_erdiagram.egg-info/SOURCES.txt
sphinx_erdiagram.egg-info/dependency_links.txt
sphinx_erdiagram.egg-info/not-zip-safe
sphinx_erdiagram.egg-info/requires.txt
sphinx_erdiagram.egg-info/top_level.txt