Metadata-Version: 1.1
Name: sphinx-erdiagram
Version: 0.0.1.dev20160527
Summary: Sphinx "ER diagram" extension
Home-page: https://github.com/myyasuda/sphinx_erdiagram
Author: myasuda
Author-email: myasuda@uchida.co.jp
License: MIT
Download-URL: http://pypi.python.org/pypi/sphinx_erdiagram
Platform: any
Classifier: Development Status :: 4 - Beta
Classifier: Environment :: Console
Classifier: Environment :: Web Environment
Classifier: Intended Audience :: Developers
Classifier: License :: OSI Approved :: MIT License
Classifier: Operating System :: OS Independent
Classifier: Programming Language :: Python
Classifier: Framework :: Sphinx :: Extension
Classifier: Topic :: Documentation
Classifier: Topic :: Utilities
